RootInteractive/__init__.py
RootInteractive/InteractiveDrawing/__init__.py
RootInteractive/InteractiveDrawing/bokeh/CDSAlias.py
RootInteractive/InteractiveDrawing/bokeh/CDSAlias.ts
RootInteractive/InteractiveDrawing/bokeh/CDSCompress.py
RootInteractive/InteractiveDrawing/bokeh/CDSCompress.ts
RootInteractive/InteractiveDrawing/bokeh/CDSJoin.py
RootInteractive/InteractiveDrawing/bokeh/CDSJoin.ts
RootInteractive/InteractiveDrawing/bokeh/CDSStack.py
RootInteractive/InteractiveDrawing/bokeh/CDSStack.ts
RootInteractive/InteractiveDrawing/bokeh/ClientLinearFitter.py
RootInteractive/InteractiveDrawing/bokeh/ClientLinearFitter.ts
RootInteractive/InteractiveDrawing/bokeh/ColumnFilter.py
RootInteractive/InteractiveDrawing/bokeh/ColumnFilter.ts
RootInteractive/InteractiveDrawing/bokeh/ConcatenatedString.py
RootInteractive/InteractiveDrawing/bokeh/ConcatenatedString.ts
RootInteractive/InteractiveDrawing/bokeh/CustomJSNAryFunction.py
RootInteractive/InteractiveDrawing/bokeh/CustomJSNAryFunction.ts
RootInteractive/InteractiveDrawing/bokeh/DownsamplerCDS.py
RootInteractive/InteractiveDrawing/bokeh/DownsamplerCDS.ts
RootInteractive/InteractiveDrawing/bokeh/HistoNdCDS.py
RootInteractive/InteractiveDrawing/bokeh/HistoNdCDS.ts
RootInteractive/InteractiveDrawing/bokeh/HistoNdProfile.py
RootInteractive/InteractiveDrawing/bokeh/HistoNdProfile.ts
RootInteractive/InteractiveDrawing/bokeh/HistoStatsCDS.py
RootInteractive/InteractiveDrawing/bokeh/HistoStatsCDS.ts
RootInteractive/InteractiveDrawing/bokeh/HistogramCDS.py
RootInteractive/InteractiveDrawing/bokeh/HistogramCDS.ts
RootInteractive/InteractiveDrawing/bokeh/LazyIntersectionFilter.py
RootInteractive/InteractiveDrawing/bokeh/LazyIntersectionFilter.ts
RootInteractive/InteractiveDrawing/bokeh/LazyTabs.py
RootInteractive/InteractiveDrawing/bokeh/LazyTabs.ts
RootInteractive/InteractiveDrawing/bokeh/MathUtils.ts
RootInteractive/InteractiveDrawing/bokeh/MultiSelectFilter.py
RootInteractive/InteractiveDrawing/bokeh/MultiSelectFilter.ts
RootInteractive-0.1.10.dist-info/METADATA
RootInteractive-0.1.10.dist-info/WHEEL
RootInteractive-0.1.10.dist-info/top_level.txt
RootInteractive-0.1.10.dist-info/RECORD
