Metadata-Version: 2.1
Name: RootInteractive
Version: 0.1.10
Summary: UNKNOWN
Home-page: https://github.com/miranov25/RootInteractive
Author: Marian I. Ivanov, Marian Ivanov  
Author-email: marian.ivanov@cern.ch, marian.i@cern.ch
License: Not defined yet. Most probably similar to ALICE (CERN)  license
Platform: UNKNOWN
Requires-Dist: numpy
Requires-Dist: scipy
Requires-Dist: pandas
Requires-Dist: anytree
Requires-Dist: nbval
Requires-Dist: tabulate
Requires-Dist: iminuit
Requires-Dist: bokeh <=2.5,>2.3
Requires-Dist: matplotlib
Requires-Dist: ipywidgets
Requires-Dist: runtime
Requires-Dist: requests
Requires-Dist: scikit-learn
Requires-Dist: scikit-hep
Requires-Dist: jinja2 ==3.0.3
Requires-Dist: jupyter
